[["Sofia","Riemann", "takeTurn", 2]]
 {"board": {"connectors":[["│","┬","─","│","┘","┬","└"], ["┼","┼","┬","│","┌","│","┬"], ["┼","─","│","│","├","─","┤"], ["┬","─","┐","│","┼","│","┬"], ["┤","└","─","┬","┬","├","┴"], ["┤","│","┬","─","┐","└","┬"], ["│","┬","├","┴","┬","┼","┬"]], "treasures":[[["alexandrite-pear-shape","alexandrite"],["alexandrite","amethyst"],["amethyst","ametrine"],["ametrine","ammolite"],["ammolite","apatite"],["apatite","aplite"],["aplite","aquamarine"]],[["aquamarine","aventurine"],["aventurine","azurite"],["azurite","beryl"],["beryl","carnelian"],["carnelian","chrysolite"],["chrysolite","citrine"],["citrine","clinohumite"]],[["clinohumite","cordierite"],["cordierite","diamond"],["diamond","dumortierite"],["dumortierite","emerald"],["emerald","garnet"],["garnet","goldstone"],["goldstone","grandidierite"]],[["grandidierite","hackmanite"],["hackmanite","heliotrope"],["heliotrope","hematite"],["hematite","jasper"],["jasper","jaspilite"],["jaspilite","kunzite"],["kunzite","labradorite"]],[["labradorite","magnesite"],["magnesite","moonstone"],["moonstone","peridot"],["peridot","prasiolite"],["prasiolite","prehnite"],["prehnite","rhodonite"],["rhodonite","ruby"]],[["ruby","sphalerite"],["sphalerite","spinel"],["spinel","stilbite"],["stilbite","sunstone"],["sunstone","tourmaline"],["tourmaline","unakite"],["unakite","zircon"]],[["zircon","zoisite"],["zoisite","super-seven"],["super-seven","ruby-diamond-profile"],["ruby-diamond-profile","star-cabochon"],["star-cabochon","raw-beryl"],["raw-beryl","purple-oval"],["purple-oval","pink-spinel-cushion"]]]}, "last":null, "plmt":[{"color":"pink", "current":{"column#":0,"row#":0}, "goto":{"column#":1,"row#":1}, "home":{"column#":3,"row#":3}}], "spare":{"1-image":"padparadscha-sapphire","2-image":"pink-round","tilekey":"│"}} 

